cpm/.gitignore
cpm/LICENSE
cpm/README.md
cpm/__init__.py
cpm/__main__.py
cpm/cpmIcon.txt
cpm/conf/app_template/app_name.cpp-tpl
cpm/conf/app_template/include/app_name.hpp-tpl
cpm/conf/app_template/source/app_name.cpp-tpl
cpm/conf/project_template/entry_point.cpp-tpl
cpm/core/__init__.py
cpm/core/base.py
cpm/core/color.py
cpm/core/template.py
cpm/core/commands/__init__.py
cpm/core/commands/init.py
cpm/core/commands/makeapp.py
cpm/core/commands/run.py
cpm/utils/__init__.py
cpm/utils/base.py
cpm/utils/config.py
cpm/utils/exceptions.py
cpm/utils/version.py
cpp_projects_manager_cli-1.0.2.dist-info/LICENSE
cpp_projects_manager_cli-1.0.2.dist-info/METADATA
cpp_projects_manager_cli-1.0.2.dist-info/WHEEL
cpp_projects_manager_cli-1.0.2.dist-info/top_level.txt
cpp_projects_manager_cli-1.0.2.dist-info/RECORD
