Metadata-Version: 2.1
Name: cpp-projects-manager-cli
Version: 1.0.2
Summary: A Python package for the creation of a CPM project.
Home-page: UNKNOWN
Author: Aashish Panchal
Author-email: aipanchal51@gmail.com
License: UNKNOWN
Keywords: cpm,c++ with python
Platform: UNKNOWN
Classifier: Programming Language :: Python :: 3
Classifier: Development Status :: 1 - Planning
Classifier: Intended Audience :: Developers
Classifier: Operating System :: Unix
Classifier: Operating System :: MacOS :: MacOS X
Classifier: Operating System :: Microsoft :: Windows
License-File: LICENSE
